NuFaster/__init__.py
NuFaster/get_library_depand.py
NuFaster/get_library_dll.py
NuFaster/nuitka_parser.py
NuFaster/setting.py
NuFaster/to_pack.py
NuFaster/tools.py
NuFaster-0.0.3.dist-info/METADATA
NuFaster-0.0.3.dist-info/WHEEL
NuFaster-0.0.3.dist-info/top_level.txt
NuFaster-0.0.3.dist-info/RECORD
